{
	"configurations" : 
	[
		{
			"directories" : 
			[
				{
					"build" : ".",
					"jsonFile" : "directory-.-Debug-d0094a50bb2071803777.json",
					"minimumCMakeVersion" : 
					{
						"string" : "3.25"
					},
					"projectIndex" : 0,
					"source" : ".",
					"targetIndexes" : 
					[
						0
					]
				}
			],
			"name" : "Debug",
			"projects" : 
			[
				{
					"directoryIndexes" : 
					[
						0
					],
					"name" : "ED1FakeNews",
					"targetIndexes" : 
					[
						0
					]
				}
			],
			"targets" : 
			[
				{
					"directoryIndex" : 0,
					"id" : "ED1FakeNews::@6890427a1f51a3e7e1df",
					"jsonFile" : "target-ED1FakeNews-Debug-d71d8c3608d77b915a49.json",
					"name" : "ED1FakeNews",
					"projectIndex" : 0
				}
			]
		}
	],
	"kind" : "codemodel",
	"paths" : 
	{
		"build" : "R:/Desktop/ED1FakeNewsListaEnlazadaSimple/cmake-build-debug",
		"source" : "R:/Desktop/ED1FakeNewsListaEnlazadaSimple"
	},
	"version" : 
	{
		"major" : 2,
		"minor" : 4
	}
}
